pmnb/__init__.py
pmnb/analyse.py
pmnb/feed.py
pmnb/growth.py
pmnb/jsq.py
pmnb-0.2.1.dist-info/licenses/LICENSE
pmnb-0.2.1.dist-info/METADATA
pmnb-0.2.1.dist-info/WHEEL
pmnb-0.2.1.dist-info/top_level.txt
pmnb-0.2.1.dist-info/RECORD
