Metadata-Version: 2.4
Name: pmnb
Version: 0.2.1
Summary: '产品经理常用工具箱'
Author: likun.pm
Author-email: likun2440@gmail.com
Classifier: Programming Language :: Python :: 3
Classifier: License :: OSI Approved :: MIT License
Classifier: Operating System :: OS Independent
Requires-Python: >=3.6
License-File: LICENSE
Requires-Dist: numpy
Requires-Dist: pandas
Requires-Dist: scipy
Requires-Dist: scikit-learn
Requires-Dist: xgboost
Requires-Dist: prettytable
Requires-Dist: matplotlib
Requires-Dist: jieba
Requires-Dist: statsmodels
Requires-Dist: seaborn
Requires-Dist: lightgbm
Dynamic: license-file
